[
  {
    "title": "CSVO - Community Shaders Visual Overhaul",
    "description": "A full Community Shaders PBR Visual Overhaul baseline",
    "author": "Bottle",
    "maintainers": [
      "github/InTheBottle"
    ],
    "game": "skyrimspecialedition",
    "official": true,
    "tags": [
      "SFW",
      "Steam",
      "Vanilla\u002B",
      "Utility",
      "official"
    ],
    "nsfw": false,
    "utility_list": false,
    "image_contains_title": true,
    "DisplayVersionOnlyInInstallerView": false,
    "force_down": false,
    "links": {
      "image": "https://raw.githubusercontent.com/InTheBottle/CSVO/main/Resources/csvo.png",
      "readme": "https://github.com/InTheBottle/CSVO/blob/main/README.md",
      "download": "https://authored-files.wabbajack.org/CSVO.wabbajack_f81bb812-a48b-4829-81a9-3c35143553d8",
      "machineURL": "CSVO",
      "discordURL": "https://discord.gg/bungalo",
      "websiteURL": ""
    },
    "download_metadata": {
      "Hash": "PW8Cy06t7+E=",
      "Size": 963641085,
      "NumberOfArchives": 455,
      "SizeOfArchives": 61984099111,
      "NumberOfInstalledFiles": 105741,
      "SizeOfInstalledFiles": 90661196289,
      "TotalSize": 152645295400
    },
    "version": "2.1.1",
    "dateCreated": "1970-01-01T00:00:00Z",
    "dateUpdated": "2025-11-28T16:18:15.3813425Z",
    "repositoryName": ""
  },
  {
    "title": "BottleRim",
    "description": "A total survival difficulty based gameplay overhaul using SimonRim and Community Shaders. Focused on modern combat for both first and third person, and heavy immersion.",
    "author": "Bottle",
    "maintainers": [
      "github/InTheBottle"
    ],
    "game": "skyrimspecialedition",
    "official": true,
    "tags": [
      "SFW",
      "Steam",
      "Vanilla\u002B",
      "official"
    ],
    "nsfw": false,
    "utility_list": false,
    "image_contains_title": true,
    "DisplayVersionOnlyInInstallerView": false,
    "force_down": false,
    "links": {
      "image": "https://raw.githubusercontent.com/InTheBottle/BottleRim/refs/heads/main/Resources/Skyrim.webp",
      "readme": "https://github.com/InTheBottle/BottleRim/blob/main/README.md",
      "download": "https://authored-files.wabbajack.org/BottleRim.wabbajack_3f9461b5-b77e-4773-ae42-dffce1706412",
      "machineURL": "BottleRim",
      "discordURL": "https://discord.gg/bungalo",
      "websiteURL": ""
    },
    "download_metadata": {
      "Hash": "viIN4+qspqc=",
      "Size": 1619270729,
      "NumberOfArchives": 2347,
      "SizeOfArchives": 134984108790,
      "NumberOfInstalledFiles": 293501,
      "SizeOfInstalledFiles": 224910093712,
      "TotalSize": 359894202502
    },
    "version": "1.2.0",
    "dateCreated": "1970-01-01T00:00:00Z",
    "dateUpdated": "2025-12-15T00:29:40.4676179Z",
    "repositoryName": ""
  }
]